starlette_jsonapi/__init__.py
starlette_jsonapi/constants.py
starlette_jsonapi/exceptions.py
starlette_jsonapi/fields.py
starlette_jsonapi/meta.py
starlette_jsonapi/openapi.py
starlette_jsonapi/pagination.py
starlette_jsonapi/resource.py
starlette_jsonapi/responses.py
starlette_jsonapi/schema.py
starlette_jsonapi/utils.py
starlette_jsonapi-2.2.1.dist-info/LICENSE
starlette_jsonapi-2.2.1.dist-info/METADATA
starlette_jsonapi-2.2.1.dist-info/WHEEL
starlette_jsonapi-2.2.1.dist-info/top_level.txt
starlette_jsonapi-2.2.1.dist-info/RECORD
