Metadata-Version: 2.1
Name: starlette-jsonapi
Version: 2.2.1
Summary: Tiny wrapper on starlette and marshmallow-jsonapi for fast JSON:API compliant python services.
Home-page: https://github.com/vladmunteanu/starlette-jsonapi
Author: Vlad Stefan Munteanu
Author-email: vladstefanmunteanu@gmail.com
License: MIT License
Classifier: Development Status :: 3 - Alpha
Classifier: Intended Audience :: Developers
Classifier: License :: OSI Approved :: MIT License
Classifier: Topic :: Internet :: WWW/HTTP
Classifier: Programming Language :: Python
Classifier: Programming Language :: Python :: 3
Classifier: Programming Language :: Python :: 3.7
Classifier: Programming Language :: Python :: 3.8
Classifier: Programming Language :: Python :: 3.9
Classifier: Programming Language :: Python :: 3.10
Classifier: Programming Language :: Python :: Implementation :: CPython
License-File: LICENSE
Requires-Dist: starlette (>=0.14.2)
Requires-Dist: apispec (>4)
Requires-Dist: marshmallow (>=3)
Requires-Dist: marshmallow-jsonapi (>=0.24.0)
